cookies_statistics/__init__.py
cookies_statistics-0.0.1.dist-info/METADATA
cookies_statistics-0.0.1.dist-info/WHEEL
cookies_statistics-0.0.1.dist-info/licenses/LICENSE
cookies_statistics-0.0.1.dist-info/RECORD
