Metadata-Version: 2.1
Name: cookies_statistics
Version: 0.0.1
Summary: Utility functions for statistical analyses.
Project-URL: GitHub, https://github.com/CookieBox26/cookies_statistics
Project-URL: Documentation, https://cookies-statistics.readthedocs.io/en/stable/
Author-email: CookieBox26 <cookie-box@cookie-box.info>
License-File: LICENSE
Classifier: License :: OSI Approved :: MIT License
Classifier: Operating System :: OS Independent
Classifier: Programming Language :: Python :: 3
Requires-Python: >=3.8
Requires-Dist: numpy>=1.25.1
Provides-Extra: dev
Requires-Dist: pytest>=7.4.0; extra == 'dev'
